avm/__init__.py
avm/errors.py
avm/ext.py
avm/main.py
avm/pattern.py
avm/types.py
avm/usefull_patterns.py
python_avm-0.9.8.dist-info/LICENSE
python_avm-0.9.8.dist-info/METADATA
python_avm-0.9.8.dist-info/WHEEL
python_avm-0.9.8.dist-info/top_level.txt
python_avm-0.9.8.dist-info/RECORD
