Metadata-Version: 2.1
Name: python-avm
Version: 0.9.8
Summary: This module allows you to check variables types, create new custom types and many others usefull features.
Home-page: https://github.com/Grosse-pasteque/AVM/
Author: Grosse-pasteque
Author-email: grossepasteque.gamer34@gmail.com
License: MIT
Project-URL: Source, https://github.com/Grosse-pasteque/AVM/
Keywords: type-checking,function-args-checking,custom-types,better-types,function-args-convertion
Platform: UNKNOWN
Classifier: Development Status :: 5 - Production/Stable
Classifier: Intended Audience :: Developers
Classifier: Topic :: Software Development :: Build Tools
Classifier: License :: OSI Approved :: MIT License
Classifier: Programming Language :: Python :: 3
Classifier: Programming Language :: Python :: 3.9
Classifier: Programming Language :: Python :: 3.10
Classifier: Programming Language :: Python :: 3 :: Only
Requires-Python: >=3.7, <4
License-File: LICENSE
